nepali_translator/__init__.py
nepali_translator/converter.py
nepali_translator/mappings.py
nepali_translator/test.py
nepali_translator/test_conversion.py
nepali_translator/translator.py
roman_nepali_translator-0.1.1.dist-info/METADATA
roman_nepali_translator-0.1.1.dist-info/WHEEL
roman_nepali_translator-0.1.1.dist-info/top_level.txt
roman_nepali_translator-0.1.1.dist-info/RECORD
