Metadata-Version: 2.1
Name: roman-nepali-translator
Version: 0.1.1
Summary: A package for translating Romanized English to Unicode Nepali
Home-page: https://github.com/MILANydv/nepali_translator_package.git
Author: Milan Yadav
Author-email: ymilan.projects@gmail.com
Classifier: Development Status :: 3 - Alpha
Classifier: License :: OSI Approved :: MIT License
Classifier: Programming Language :: Python
Classifier: Programming Language :: Python :: 3
Classifier: Programming Language :: Python :: 3.6
Classifier: Programming Language :: Python :: 3.7
Classifier: Programming Language :: Python :: 3.8
Classifier: Programming Language :: Python :: 3.9
